cachepy/__init__.py
cachepy/conf.py
cachepy/crypter.py
cachepy/test.py
cachepy/utils.py
cachepy/backends/__init__.py
cachepy/backends/base.py
cachepy/backends/file_backend.py
cachepy/backends/memory_backend.py
cachepy-1.2-py3.7.egg-info/PKG-INFO
cachepy-1.2-py3.7.egg-info/SOURCES.txt
cachepy-1.2-py3.7.egg-info/dependency_links.txt
cachepy-1.2-py3.7.egg-info/top_level.txt
cachepy-1.2.dist-info/LICENSE
cachepy-1.2.dist-info/METADATA
cachepy-1.2.dist-info/WHEEL
cachepy-1.2.dist-info/top_level.txt
cachepy-1.2.dist-info/RECORD
