Metadata-Version: 2.1
Name: cachepy
Version: 1.2
Summary: Caching results of functions in Python
Home-page: https://github.com/scidam/cachepy
Author: Dmitry Kislov
Author-email: kislov@easydan.com
License: UNKNOWN
Keywords: caching,python,file-based cache,memory-based cache,encrypted cache
Platform: UNKNOWN
Classifier: Development Status :: 5 - Production/Stable
Classifier: License :: OSI Approved :: MIT License
Classifier: Operating System :: OS Independent
Classifier: Programming Language :: Python
Classifier: Programming Language :: Python :: 2
Classifier: Programming Language :: Python :: 2.7
Classifier: Programming Language :: Python :: 3
Classifier: Programming Language :: Python :: 3.3
Classifier: Programming Language :: Python :: 3.4
Classifier: Programming Language :: Python :: 3.5
Classifier: Programming Language :: Python :: 3.6
Classifier: Programming Language :: Python :: 3.7
Classifier: Programming Language :: Python :: 3.8
Classifier: Programming Language :: Python :: 3.9
Classifier: Topic :: Software Development
Classifier: Intended Audience :: Developers
